cfid/__init__.py
cfid/identifier.py
cfid-0.1.1.dist-info/LICENSE
cfid-0.1.1.dist-info/METADATA
cfid-0.1.1.dist-info/WHEEL
cfid-0.1.1.dist-info/RECORD
